MANIFEST.in
README.rst
setup.cfg
setup.py
ckanext/__init__.py
ckanext/ddug/__init__.py
ckanext/ddug/plugin.py
ckanext/ddug/tests/__init__.py
ckanext/ddug/tests/test_plugin.py
ckanext_ddug.egg-info/PKG-INFO
ckanext_ddug.egg-info/SOURCES.txt
ckanext_ddug.egg-info/dependency_links.txt
ckanext_ddug.egg-info/entry_points.txt
ckanext_ddug.egg-info/pbr.json
ckanext_ddug.egg-info/top_level.txt