Metadata-Version: 1.1
Name: ckanext-ddug
Version: 0.0.1
Summary: Extension to manage datadotug
Home-page: https://github.com/datadotug/ckanext-ddug
Author: Dan Mulindwa
Author-email: dmulindwa@gmail.com
License: AGPL
Keywords: CKAN Datadotug initial settings
Platform: UNKNOWN
Classifier: Development Status :: 4 - Beta
Classifier: License :: OSI Approved :: GNU Affero General Public License v3 or later (AGPLv3+)
Classifier: Programming Language :: Python :: 2.6
Classifier: Programming Language :: Python :: 2.7
